hassfeld/__init__.py
hassfeld/aioupnp.py
hassfeld/auxilliary.py
hassfeld/common.py
hassfeld/constants.py
hassfeld/dlna.py
hassfeld/logging.py
hassfeld/upnp.py
hassfeld/webservice.py
hassfeld-0.3.13a2.dist-info/LICENSE
hassfeld-0.3.13a2.dist-info/METADATA
hassfeld-0.3.13a2.dist-info/WHEEL
hassfeld-0.3.13a2.dist-info/top_level.txt
hassfeld-0.3.13a2.dist-info/RECORD
