Metadata-Version: 2.1
Name: hassfeld
Version: 0.3.13a2
Summary: Integration of Raumfeld into Home Assistant
Home-page: https://github.com/B5r1oJ0A9G/hassfeld
Classifier: Programming Language :: Python :: 3
Classifier: License :: OSI Approved :: GNU General Public License v3 (GPLv3)
Classifier: Operating System :: OS Independent
Requires-Python: >=3.5
License-File: LICENSE
Requires-Dist: aiohttp
Requires-Dist: async-upnp-client (>=0.27)
Requires-Dist: requests
Requires-Dist: xmltodict
